{
  "metadata" : {
    "identifier" : "https://nhattruyenz.com/truyen-tranh/thanh-guom-diet-quy",
    "title" : "Thanh Gươm Diệt Quỷ",
    "subtitle" : null,
    "author" : null,
    "narrator" : null,
    "language" : "vi",
    "description" : null,
    "publisher" : "N/A",
    "subject" : null,
    "modified" : null,
    "published" : "2023-05-01",
    "duration" : 0,
    "abridged" : false,
    "conformsTo" : "https://readium.org/webpub-manifest/profiles/divina",
    "numberOfPages" : 222,
    "readingProgression" : "ttb",
    "belongsTo" : null,
    "presentation" : {
      "fit" : "width",
      "overflow" : "scrolled",
      "continuous" : true
    },
    "@type" : null,
    "schema:license" : null
  },
  "links" : [ {
    "rel" : "self",
    "href" : "https://raw.githubusercontent.com/thuvienonline40/book_storage_collection/main/comic_manifest.json",
    "type" : "application/divina+json"
  } ],
  "readingOrder" : [ {
    "href" : "https://raw.githubusercontent.com/tracuumasothue40/comic_storage_two7/main/IMAGE/IMAGE_d460fa336d7f3c4049b0d4c9d0ef66fd_fe63b91deece3b4eeb3dc90528a9d9c2_c75fef902708d3b1f54271cebe8ad332.jpg",
    "type" : "image/jpeg",
    "bitrate" : 0,
    "duration" : 0,
    "title" : null,
    "properties" : null,
    "alternate" : [ {
      "href" : "https://img.abctruyen.xyz/mt-sv-image/app/public/uploads/2020-12-10/672560/0.jpg",
      "type" : "image/jpeg",
      "bitrate" : 0,
      "duration" : 0,
      "title" : null,
      "properties" : null,
      "alternate" : null
    }, {
      "href" : "https://i2.wp.com/img.abctruyen.xyz/mt-sv-image/app/public/uploads/2020-12-10/672560/0.jpg",
      "type" : "image/jpeg",
      "bitrate" : 0,
      "duration" : 0,
      "title" : null,
      "properties" : null,
      "alternate" : null
    } ]
  }, {
    "href" : "https://raw.githubusercontent.com/tracuumasothue40/comic_storage_two7/main/IMAGE/IMAGE_d460fa336d7f3c4049b0d4c9d0ef66fd_fe63b91deece3b4eeb3dc90528a9d9c2_458b8aa55827a465dd4b9d68fd27ab13.jpg",
    "type" : "image/jpeg",
    "bitrate" : 0,
    "duration" : 0,
    "title" : null,
    "properties" : null,
    "alternate" : [ {
      "href" : "https://img.abctruyen.xyz/mt-sv-image/app/public/uploads/2020-12-10/672560/1.jpg",
      "type" : "image/jpeg",
      "bitrate" : 0,
      "duration" : 0,
      "title" : null,
      "properties" : null,
      "alternate" : null
    }, {
      "href" : "https://i2.wp.com/img.abctruyen.xyz/mt-sv-image/app/public/uploads/2020-12-10/672560/1.jpg",
      "type" : "image/jpeg",
      "bitrate" : 0,
      "duration" : 0,
      "title" : null,
      "properties" : null,
      "alternate" : null
    } ]
  }, {
    "href" : "https://raw.githubusercontent.com/tracuumasothue40/comic_storage_two7/main/IMAGE/IMAGE_d460fa336d7f3c4049b0d4c9d0ef66fd_fe63b91deece3b4eeb3dc90528a9d9c2_950ca79d70016723a73ab368fea2ebcf.jpg",
    "type" : "image/jpeg",
    "bitrate" : 0,
    "duration" : 0,
    "title" : null,
    "properties" : null,
    "alternate" : [ {
      "href" : "https://img.abctruyen.xyz/mt-sv-image/app/public/uploads/2020-12-10/672560/2.jpg",
      "type" : "image/jpeg",
      "bitrate" : 0,
      "duration" : 0,
      "title" : null,
      "properties" : null,
      "alternate" : null
    }, {
      "href" : "https://i2.wp.com/img.abctruyen.xyz/mt-sv-image/app/public/uploads/2020-12-10/672560/2.jpg",
      "type" : "image/jpeg",
      "bitrate" : 0,
      "duration" : 0,
      "title" : null,
      "properties" : null,
      "alternate" : null
    } ]
  }, {
    "href" : "https://raw.githubusercontent.com/tracuumasothue40/comic_storage_two7/main/IMAGE/IMAGE_d460fa336d7f3c4049b0d4c9d0ef66fd_fe63b91deece3b4eeb3dc90528a9d9c2_e296aa020d5bd063e7e4884ff1e580d1.jpg",
    "type" : "image/jpeg",
    "bitrate" : 0,
    "duration" : 0,
    "title" : null,
    "properties" : null,
    "alternate" : [ {
      "href" : "https://img.abctruyen.xyz/mt-sv-image/app/public/uploads/2020-12-10/672560/3.jpg",
      "type" : "image/jpeg",
      "bitrate" : 0,
      "duration" : 0,
      "title" : null,
      "properties" : null,
      "alternate" : null
    }, {
      "href" : "https://i2.wp.com/img.abctruyen.xyz/mt-sv-image/app/public/uploads/2020-12-10/672560/3.jpg",
      "type" : "image/jpeg",
      "bitrate" : 0,
      "duration" : 0,
      "title" : null,
      "properties" : null,
      "alternate" : null
    } ]
  }, {
    "href" : "https://raw.githubusercontent.com/tracuumasothue40/comic_storage_two7/main/IMAGE/IMAGE_d460fa336d7f3c4049b0d4c9d0ef66fd_fe63b91deece3b4eeb3dc90528a9d9c2_0c0376403e42027c3c8a4c90920ff849.jpg",
    "type" : "image/jpeg",
    "bitrate" : 0,
    "duration" : 0,
    "title" : null,
    "properties" : null,
    "alternate" : [ {
      "href" : "https://img.abctruyen.xyz/mt-sv-image/app/public/uploads/2020-12-10/672560/4.jpg",
      "type" : "image/jpeg",
      "bitrate" : 0,
      "duration" : 0,
      "title" : null,
      "properties" : null,
      "alternate" : null
    }, {
      "href" : "https://i2.wp.com/img.abctruyen.xyz/mt-sv-image/app/public/uploads/2020-12-10/672560/4.jpg",
      "type" : "image/jpeg",
      "bitrate" : 0,
      "duration" : 0,
      "title" : null,
      "properties" : null,
      "alternate" : null
    } ]
  }, {
    "href" : "https://raw.githubusercontent.com/tracuumasothue40/comic_storage_two7/main/IMAGE/IMAGE_d460fa336d7f3c4049b0d4c9d0ef66fd_fe63b91deece3b4eeb3dc90528a9d9c2_c21811205c3ac83b9786b3a3298e9886.jpg",
    "type" : "image/jpeg",
    "bitrate" : 0,
    "duration" : 0,
    "title" : null,
    "properties" : null,
    "alternate" : [ {
      "href" : "https://img.abctruyen.xyz/mt-sv-image/app/public/uploads/2020-12-10/672560/5.jpg",
      "type" : "image/jpeg",
      "bitrate" : 0,
      "duration" : 0,
      "title" : null,
      "properties" : null,
      "alternate" : null
    }, {
      "href" : "https://i2.wp.com/img.abctruyen.xyz/mt-sv-image/app/public/uploads/2020-12-10/672560/5.jpg",
      "type" : "image/jpeg",
      "bitrate" : 0,
      "duration" : 0,
      "title" : null,
      "properties" : null,
      "alternate" : null
    } ]
  }, {
    "href" : "https://raw.githubusercontent.com/tracuumasothue40/comic_storage_two7/main/IMAGE/IMAGE_d460fa336d7f3c4049b0d4c9d0ef66fd_fe63b91deece3b4eeb3dc90528a9d9c2_026565f157e6b6a0a9841c6ba99746f0.jpg",
    "type" : "image/jpeg",
    "bitrate" : 0,
    "duration" : 0,
    "title" : null,
    "properties" : null,
    "alternate" : [ {
      "href" : "https://img.abctruyen.xyz/mt-sv-image/app/public/uploads/2020-12-10/672560/6.jpg",
      "type" : "image/jpeg",
      "bitrate" : 0,
      "duration" : 0,
      "title" : null,
      "properties" : null,
      "alternate" : null
    }, {
      "href" : "https://i2.wp.com/img.abctruyen.xyz/mt-sv-image/app/public/uploads/2020-12-10/672560/6.jpg",
      "type" : "image/jpeg",
      "bitrate" : 0,
      "duration" : 0,
      "title" : null,
      "properties" : null,
      "alternate" : null
    } ]
  }, {
    "href" : "https://raw.githubusercontent.com/tracuumasothue40/comic_storage_two7/main/IMAGE/IMAGE_d460fa336d7f3c4049b0d4c9d0ef66fd_fe63b91deece3b4eeb3dc90528a9d9c2_2e39da2b81764c048fe3db34b9067e3e.jpg",
    "type" : "image/jpeg",
    "bitrate" : 0,
    "duration" : 0,
    "title" : null,
    "properties" : null,
    "alternate" : [ {
      "href" : "https://img.abctruyen.xyz/mt-sv-image/app/public/uploads/2020-12-10/672560/7.jpg",
      "type" : "image/jpeg",
      "bitrate" : 0,
      "duration" : 0,
      "title" : null,
      "properties" : null,
      "alternate" : null
    }, {
      "href" : "https://i2.wp.com/img.abctruyen.xyz/mt-sv-image/app/public/uploads/2020-12-10/672560/7.jpg",
      "type" : "image/jpeg",
      "bitrate" : 0,
      "duration" : 0,
      "title" : null,
      "properties" : null,
      "alternate" : null
    } ]
  }, {
    "href" : "https://raw.githubusercontent.com/tracuumasothue40/comic_storage_two7/main/IMAGE/IMAGE_d460fa336d7f3c4049b0d4c9d0ef66fd_fe63b91deece3b4eeb3dc90528a9d9c2_4d2552fae08b8ad2a4494e88915e0837.jpg",
    "type" : "image/jpeg",
    "bitrate" : 0,
    "duration" : 0,
    "title" : null,
    "properties" : null,
    "alternate" : [ {
      "href" : "https://img.abctruyen.xyz/mt-sv-image/app/public/uploads/2020-12-10/672560/8.jpg",
      "type" : "image/jpeg",
      "bitrate" : 0,
      "duration" : 0,
      "title" : null,
      "properties" : null,
      "alternate" : null
    }, {
      "href" : "https://i2.wp.com/img.abctruyen.xyz/mt-sv-image/app/public/uploads/2020-12-10/672560/8.jpg",
      "type" : "image/jpeg",
      "bitrate" : 0,
      "duration" : 0,
      "title" : null,
      "properties" : null,
      "alternate" : null
    } ]
  }, {
    "href" : "https://raw.githubusercontent.com/tracuumasothue40/comic_storage_two7/main/IMAGE/IMAGE_d460fa336d7f3c4049b0d4c9d0ef66fd_fe63b91deece3b4eeb3dc90528a9d9c2_02bff3ea344d2bef365e22ac2e08ab65.jpg",
    "type" : "image/jpeg",
    "bitrate" : 0,
    "duration" : 0,
    "title" : null,
    "properties" : null,
    "alternate" : [ {
      "href" : "https://img.abctruyen.xyz/mt-sv-image/app/public/uploads/2020-12-10/672560/9.jpg",
      "type" : "image/jpeg",
      "bitrate" : 0,
      "duration" : 0,
      "title" : null,
      "properties" : null,
      "alternate" : null
    }, {
      "href" : "https://i2.wp.com/img.abctruyen.xyz/mt-sv-image/app/public/uploads/2020-12-10/672560/9.jpg",
      "type" : "image/jpeg",
      "bitrate" : 0,
      "duration" : 0,
      "title" : null,
      "properties" : null,
      "alternate" : null
    } ]
  }, {
    "href" : "https://raw.githubusercontent.com/tracuumasothue40/comic_storage_two7/main/IMAGE/IMAGE_d460fa336d7f3c4049b0d4c9d0ef66fd_fe63b91deece3b4eeb3dc90528a9d9c2_fbedf48e10ef14c395fe62c5f9bbf15d.jpg",
    "type" : "image/jpeg",
    "bitrate" : 0,
    "duration" : 0,
    "title" : null,
    "properties" : null,
    "alternate" : [ {
      "href" : "https://img.abctruyen.xyz/mt-sv-image/app/public/uploads/2020-12-10/672560/10.jpg",
      "type" : "image/jpeg",
      "bitrate" : 0,
      "duration" : 0,
      "title" : null,
      "properties" : null,
      "alternate" : null
    }, {
      "href" : "https://i2.wp.com/img.abctruyen.xyz/mt-sv-image/app/public/uploads/2020-12-10/672560/10.jpg",
      "type" : "image/jpeg",
      "bitrate" : 0,
      "duration" : 0,
      "title" : null,
      "properties" : null,
      "alternate" : null
    } ]
  }, {
    "href" : "https://raw.githubusercontent.com/tracuumasothue40/comic_storage_two7/main/IMAGE/IMAGE_d460fa336d7f3c4049b0d4c9d0ef66fd_fe63b91deece3b4eeb3dc90528a9d9c2_60a1401dc69f82cac1ae6c50b973b83d.jpg",
    "type" : "image/jpeg",
    "bitrate" : 0,
    "duration" : 0,
    "title" : null,
    "properties" : null,
    "alternate" : [ {
      "href" : "https://img.abctruyen.xyz/mt-sv-image/app/public/uploads/2020-12-10/672560/11.jpg",
      "type" : "image/jpeg",
      "bitrate" : 0,
      "duration" : 0,
      "title" : null,
      "properties" : null,
      "alternate" : null
    }, {
      "href" : "https://i2.wp.com/img.abctruyen.xyz/mt-sv-image/app/public/uploads/2020-12-10/672560/11.jpg",
      "type" : "image/jpeg",
      "bitrate" : 0,
      "duration" : 0,
      "title" : null,
      "properties" : null,
      "alternate" : null
    } ]
  }, {
    "href" : "https://raw.githubusercontent.com/tracuumasothue40/comic_storage_two7/main/IMAGE/IMAGE_d460fa336d7f3c4049b0d4c9d0ef66fd_fe63b91deece3b4eeb3dc90528a9d9c2_779d10ac62a6438cc9518ea0d8d52ac0.jpg",
    "type" : "image/jpeg",
    "bitrate" : 0,
    "duration" : 0,
    "title" : null,
    "properties" : null,
    "alternate" : [ {
      "href" : "https://img.abctruyen.xyz/mt-sv-image/app/public/uploads/2020-12-10/672560/12.jpg",
      "type" : "image/jpeg",
      "bitrate" : 0,
      "duration" : 0,
      "title" : null,
      "properties" : null,
      "alternate" : null
    }, {
      "href" : "https://i2.wp.com/img.abctruyen.xyz/mt-sv-image/app/public/uploads/2020-12-10/672560/12.jpg",
      "type" : "image/jpeg",
      "bitrate" : 0,
      "duration" : 0,
      "title" : null,
      "properties" : null,
      "alternate" : null
    } ]
  }, {
    "href" : "https://raw.githubusercontent.com/tracuumasothue40/comic_storage_two7/main/IMAGE/IMAGE_d460fa336d7f3c4049b0d4c9d0ef66fd_fe63b91deece3b4eeb3dc90528a9d9c2_8988f2d5bb679608ff813307c5a0bf48.jpg",
    "type" : "image/jpeg",
    "bitrate" : 0,
    "duration" : 0,
    "title" : null,
    "properties" : null,
    "alternate" : [ {
      "href" : "https://img.abctruyen.xyz/mt-sv-image/app/public/uploads/2020-12-10/672560/13.jpg",
      "type" : "image/jpeg",
      "bitrate" : 0,
      "duration" : 0,
      "title" : null,
      "properties" : null,
      "alternate" : null
    }, {
      "href" : "https://i2.wp.com/img.abctruyen.xyz/mt-sv-image/app/public/uploads/2020-12-10/672560/13.jpg",
      "type" : "image/jpeg",
      "bitrate" : 0,
      "duration" : 0,
      "title" : null,
      "properties" : null,
      "alternate" : null
    } ]
  }, {
    "href" : "https://raw.githubusercontent.com/tracuumasothue40/comic_storage_two7/main/IMAGE/IMAGE_d460fa336d7f3c4049b0d4c9d0ef66fd_fe63b91deece3b4eeb3dc90528a9d9c2_4d90c15f87519b312ea4cc05fee7473b.jpg",
    "type" : "image/jpeg",
    "bitrate" : 0,
    "duration" : 0,
    "title" : null,
    "properties" : null,
    "alternate" : [ {
      "href" : "https://img.abctruyen.xyz/mt-sv-image/app/public/uploads/2020-12-10/672560/14.jpg",
      "type" : "image/jpeg",
      "bitrate" : 0,
      "duration" : 0,
      "title" : null,
      "properties" : null,
      "alternate" : null
    }, {
      "href" : "https://i2.wp.com/img.abctruyen.xyz/mt-sv-image/app/public/uploads/2020-12-10/672560/14.jpg",
      "type" : "image/jpeg",
      "bitrate" : 0,
      "duration" : 0,
      "title" : null,
      "properties" : null,
      "alternate" : null
    } ]
  }, {
    "href" : "https://raw.githubusercontent.com/tracuumasothue40/comic_storage_two7/main/IMAGE/IMAGE_d460fa336d7f3c4049b0d4c9d0ef66fd_fe63b91deece3b4eeb3dc90528a9d9c2_2308daf07561fb15114c77814dc230bf.jpg",
    "type" : "image/jpeg",
    "bitrate" : 0,
    "duration" : 0,
    "title" : null,
    "properties" : null,
    "alternate" : [ {
      "href" : "https://img.abctruyen.xyz/mt-sv-image/app/public/uploads/2020-12-10/672560/15.jpg",
      "type" : "image/jpeg",
      "bitrate" : 0,
      "duration" : 0,
      "title" : null,
      "properties" : null,
      "alternate" : null
    }, {
      "href" : "https://i2.wp.com/img.abctruyen.xyz/mt-sv-image/app/public/uploads/2020-12-10/672560/15.jpg",
      "type" : "image/jpeg",
      "bitrate" : 0,
      "duration" : 0,
      "title" : null,
      "properties" : null,
      "alternate" : null
    } ]
  }, {
    "href" : "https://raw.githubusercontent.com/tracuumasothue40/comic_storage_two7/main/IMAGE/IMAGE_d460fa336d7f3c4049b0d4c9d0ef66fd_fe63b91deece3b4eeb3dc90528a9d9c2_c8700572a049fda2bed80b570b1de525.jpg",
    "type" : "image/jpeg",
    "bitrate" : 0,
    "duration" : 0,
    "title" : null,
    "properties" : null,
    "alternate" : [ {
      "href" : "https://img.abctruyen.xyz/mt-sv-image/app/public/uploads/2020-12-10/672560/16.jpg",
      "type" : "image/jpeg",
      "bitrate" : 0,
      "duration" : 0,
      "title" : null,
      "properties" : null,
      "alternate" : null
    }, {
      "href" : "https://i2.wp.com/img.abctruyen.xyz/mt-sv-image/app/public/uploads/2020-12-10/672560/16.jpg",
      "type" : "image/jpeg",
      "bitrate" : 0,
      "duration" : 0,
      "title" : null,
      "properties" : null,
      "alternate" : null
    } ]
  }, {
    "href" : "https://raw.githubusercontent.com/tracuumasothue40/comic_storage_two7/main/IMAGE/IMAGE_d460fa336d7f3c4049b0d4c9d0ef66fd_fe63b91deece3b4eeb3dc90528a9d9c2_18f6147b5dc25766c60675f462187b28.jpg",
    "type" : "image/jpeg",
    "bitrate" : 0,
    "duration" : 0,
    "title" : null,
    "properties" : null,
    "alternate" : [ {
      "href" : "https://img.abctruyen.xyz/mt-sv-image/app/public/uploads/2020-12-10/672560/17.jpg",
      "type" : "image/jpeg",
      "bitrate" : 0,
      "duration" : 0,
      "title" : null,
      "properties" : null,
      "alternate" : null
    }, {
      "href" : "https://i2.wp.com/img.abctruyen.xyz/mt-sv-image/app/public/uploads/2020-12-10/672560/17.jpg",
      "type" : "image/jpeg",
      "bitrate" : 0,
      "duration" : 0,
      "title" : null,
      "properties" : null,
      "alternate" : null
    } ]
  }, {
    "href" : "https://raw.githubusercontent.com/tracuumasothue40/comic_storage_two7/main/IMAGE/IMAGE_d460fa336d7f3c4049b0d4c9d0ef66fd_fe63b91deece3b4eeb3dc90528a9d9c2_4ff70d729f94b80ed0a5aee5ec26c12d.jpg",
    "type" : "image/jpeg",
    "bitrate" : 0,
    "duration" : 0,
    "title" : null,
    "properties" : null,
    "alternate" : [ {
      "href" : "https://img.abctruyen.xyz/mt-sv-image/app/public/uploads/2020-12-10/672560/18.jpg",
      "type" : "image/jpeg",
      "bitrate" : 0,
      "duration" : 0,
      "title" : null,
      "properties" : null,
      "alternate" : null
    }, {
      "href" : "https://i2.wp.com/img.abctruyen.xyz/mt-sv-image/app/public/uploads/2020-12-10/672560/18.jpg",
      "type" : "image/jpeg",
      "bitrate" : 0,
      "duration" : 0,
      "title" : null,
      "properties" : null,
      "alternate" : null
    } ]
  }, {
    "href" : "https://raw.githubusercontent.com/tracuumasothue40/comic_storage_two7/main/IMAGE/IMAGE_d460fa336d7f3c4049b0d4c9d0ef66fd_fe63b91deece3b4eeb3dc90528a9d9c2_f47be0610dbafe38eaa7dad57b58ef5a.jpg",
    "type" : "image/jpeg",
    "bitrate" : 0,
    "duration" : 0,
    "title" : null,
    "properties" : null,
    "alternate" : [ {
      "href" : "https://img.abctruyen.xyz/mt-sv-image/app/public/uploads/2020-12-10/672560/19.jpg",
      "type" : "image/jpeg",
      "bitrate" : 0,
      "duration" : 0,
      "title" : null,
      "properties" : null,
      "alternate" : null
    }, {
      "href" : "https://i2.wp.com/img.abctruyen.xyz/mt-sv-image/app/public/uploads/2020-12-10/672560/19.jpg",
      "type" : "image/jpeg",
      "bitrate" : 0,
      "duration" : 0,
      "title" : null,
      "properties" : null,
      "alternate" : null
    } ]
  }, {
    "href" : "https://raw.githubusercontent.com/tracuumasothue40/comic_storage_two7/main/IMAGE/IMAGE_d460fa336d7f3c4049b0d4c9d0ef66fd_fe63b91deece3b4eeb3dc90528a9d9c2_b1f6ab8045ee21fc11609680a1c524cb.jpg",
    "type" : "image/jpeg",
    "bitrate" : 0,
    "duration" : 0,
    "title" : null,
    "properties" : null,
    "alternate" : [ {
      "href" : "https://img.abctruyen.xyz/mt-sv-image/app/public/uploads/2020-12-10/672560/20.jpg",
      "type" : "image/jpeg",
      "bitrate" : 0,
      "duration" : 0,
      "title" : null,
      "properties" : null,
      "alternate" : null
    }, {
      "href" : "https://i2.wp.com/img.abctruyen.xyz/mt-sv-image/app/public/uploads/2020-12-10/672560/20.jpg",
      "type" : "image/jpeg",
      "bitrate" : 0,
      "duration" : 0,
      "title" : null,
      "properties" : null,
      "alternate" : null
    } ]
  } ],
  "toc" : null,
  "@context" : "https://readium.org/webpub-manifest/context.jsonld"
}