{
  "metadata" : {
    "identifier" : "https://nhattruyenz.com/truyen-tranh/truong-cong-chua-ac-doc-bat-dau-chim-dam-trong",
    "title" : "Trưởng Công Chúa Ác Độc Bắt Đầu Chìm Đắm Trong Yêu Đương",
    "subtitle" : null,
    "author" : null,
    "narrator" : null,
    "language" : "vi",
    "description" : null,
    "publisher" : "N/A",
    "subject" : null,
    "modified" : null,
    "published" : "2023-05-01",
    "duration" : 0,
    "abridged" : false,
    "conformsTo" : "https://readium.org/webpub-manifest/profiles/divina",
    "numberOfPages" : 14,
    "readingProgression" : "ttb",
    "belongsTo" : null,
    "presentation" : {
      "fit" : "width",
      "overflow" : "scrolled",
      "continuous" : true
    },
    "@type" : null,
    "schema:license" : null
  },
  "links" : [ {
    "rel" : "self",
    "href" : "https://raw.githubusercontent.com/thuvienonline40/book_storage_collection/main/comic_manifest.json",
    "type" : "application/divina+json"
  } ],
  "readingOrder" : [ {
    "href" : "https://raw.githubusercontent.com/tracuumasothue40/comic_storage_two7/main/IMAGE/IMAGE_02f81e1c6377ca00b2ecc19daea2d4ba_387e9bb2d5522e2a1eb69646c6949884_15fe6aca8b6c99633edd7a9cb484f5af.jpg",
    "type" : "image/jpeg",
    "bitrate" : 0,
    "duration" : 0,
    "title" : null,
    "properties" : null,
    "alternate" : [ {
      "href" : "https://img.abctruyen.xyz/uploads/19429/chuong-14/1.jpg",
      "type" : "image/jpeg",
      "bitrate" : 0,
      "duration" : 0,
      "title" : null,
      "properties" : null,
      "alternate" : null
    }, {
      "href" : "https://i2.wp.com/img.abctruyen.xyz/uploads/19429/chuong-14/1.jpg",
      "type" : "image/jpeg",
      "bitrate" : 0,
      "duration" : 0,
      "title" : null,
      "properties" : null,
      "alternate" : null
    } ]
  }, {
    "href" : "https://raw.githubusercontent.com/tracuumasothue40/comic_storage_two7/main/IMAGE/IMAGE_02f81e1c6377ca00b2ecc19daea2d4ba_387e9bb2d5522e2a1eb69646c6949884_336443f2912bad22443a6339b8b0c0c5.jpg",
    "type" : "image/jpeg",
    "bitrate" : 0,
    "duration" : 0,
    "title" : null,
    "properties" : null,
    "alternate" : [ {
      "href" : "https://img.abctruyen.xyz/uploads/19429/chuong-14/2.jpg",
      "type" : "image/jpeg",
      "bitrate" : 0,
      "duration" : 0,
      "title" : null,
      "properties" : null,
      "alternate" : null
    }, {
      "href" : "https://i2.wp.com/img.abctruyen.xyz/uploads/19429/chuong-14/2.jpg",
      "type" : "image/jpeg",
      "bitrate" : 0,
      "duration" : 0,
      "title" : null,
      "properties" : null,
      "alternate" : null
    } ]
  }, {
    "href" : "https://raw.githubusercontent.com/tracuumasothue40/comic_storage_two7/main/IMAGE/IMAGE_02f81e1c6377ca00b2ecc19daea2d4ba_387e9bb2d5522e2a1eb69646c6949884_b8b643872db370de7673b4a8153055b7.jpg",
    "type" : "image/jpeg",
    "bitrate" : 0,
    "duration" : 0,
    "title" : null,
    "properties" : null,
    "alternate" : [ {
      "href" : "https://img.abctruyen.xyz/uploads/19429/chuong-14/3.jpg",
      "type" : "image/jpeg",
      "bitrate" : 0,
      "duration" : 0,
      "title" : null,
      "properties" : null,
      "alternate" : null
    }, {
      "href" : "https://i2.wp.com/img.abctruyen.xyz/uploads/19429/chuong-14/3.jpg",
      "type" : "image/jpeg",
      "bitrate" : 0,
      "duration" : 0,
      "title" : null,
      "properties" : null,
      "alternate" : null
    } ]
  }, {
    "href" : "https://raw.githubusercontent.com/tracuumasothue40/comic_storage_two7/main/IMAGE/IMAGE_02f81e1c6377ca00b2ecc19daea2d4ba_387e9bb2d5522e2a1eb69646c6949884_22770a0164baa4bdabcf2d29bbebe59f.jpg",
    "type" : "image/jpeg",
    "bitrate" : 0,
    "duration" : 0,
    "title" : null,
    "properties" : null,
    "alternate" : [ {
      "href" : "https://img.abctruyen.xyz/uploads/19429/chuong-14/4.jpg",
      "type" : "image/jpeg",
      "bitrate" : 0,
      "duration" : 0,
      "title" : null,
      "properties" : null,
      "alternate" : null
    }, {
      "href" : "https://i2.wp.com/img.abctruyen.xyz/uploads/19429/chuong-14/4.jpg",
      "type" : "image/jpeg",
      "bitrate" : 0,
      "duration" : 0,
      "title" : null,
      "properties" : null,
      "alternate" : null
    } ]
  }, {
    "href" : "https://raw.githubusercontent.com/tracuumasothue40/comic_storage_two7/main/IMAGE/IMAGE_02f81e1c6377ca00b2ecc19daea2d4ba_387e9bb2d5522e2a1eb69646c6949884_65d75ea4aa2961a09c39f2d3f3bada9d.jpg",
    "type" : "image/jpeg",
    "bitrate" : 0,
    "duration" : 0,
    "title" : null,
    "properties" : null,
    "alternate" : [ {
      "href" : "https://img.abctruyen.xyz/uploads/19429/chuong-14/5.jpg",
      "type" : "image/jpeg",
      "bitrate" : 0,
      "duration" : 0,
      "title" : null,
      "properties" : null,
      "alternate" : null
    }, {
      "href" : "https://i2.wp.com/img.abctruyen.xyz/uploads/19429/chuong-14/5.jpg",
      "type" : "image/jpeg",
      "bitrate" : 0,
      "duration" : 0,
      "title" : null,
      "properties" : null,
      "alternate" : null
    } ]
  }, {
    "href" : "https://raw.githubusercontent.com/tracuumasothue40/comic_storage_two7/main/IMAGE/IMAGE_02f81e1c6377ca00b2ecc19daea2d4ba_387e9bb2d5522e2a1eb69646c6949884_ff8e155deccc7ab009c5952092b71438.jpg",
    "type" : "image/jpeg",
    "bitrate" : 0,
    "duration" : 0,
    "title" : null,
    "properties" : null,
    "alternate" : [ {
      "href" : "https://img.abctruyen.xyz/uploads/19429/chuong-14/6.jpg",
      "type" : "image/jpeg",
      "bitrate" : 0,
      "duration" : 0,
      "title" : null,
      "properties" : null,
      "alternate" : null
    }, {
      "href" : "https://i2.wp.com/img.abctruyen.xyz/uploads/19429/chuong-14/6.jpg",
      "type" : "image/jpeg",
      "bitrate" : 0,
      "duration" : 0,
      "title" : null,
      "properties" : null,
      "alternate" : null
    } ]
  }, {
    "href" : "https://raw.githubusercontent.com/tracuumasothue40/comic_storage_two7/main/IMAGE/IMAGE_02f81e1c6377ca00b2ecc19daea2d4ba_387e9bb2d5522e2a1eb69646c6949884_4707657e0ea9f12806f5b440fe63a3a6.jpg",
    "type" : "image/jpeg",
    "bitrate" : 0,
    "duration" : 0,
    "title" : null,
    "properties" : null,
    "alternate" : [ {
      "href" : "https://img.abctruyen.xyz/uploads/19429/chuong-14/7.jpg",
      "type" : "image/jpeg",
      "bitrate" : 0,
      "duration" : 0,
      "title" : null,
      "properties" : null,
      "alternate" : null
    }, {
      "href" : "https://i2.wp.com/img.abctruyen.xyz/uploads/19429/chuong-14/7.jpg",
      "type" : "image/jpeg",
      "bitrate" : 0,
      "duration" : 0,
      "title" : null,
      "properties" : null,
      "alternate" : null
    } ]
  }, {
    "href" : "https://raw.githubusercontent.com/tracuumasothue40/comic_storage_two7/main/IMAGE/IMAGE_02f81e1c6377ca00b2ecc19daea2d4ba_387e9bb2d5522e2a1eb69646c6949884_ab49ff865b1ac81e6acf2c5d48bbb4ee.jpg",
    "type" : "image/jpeg",
    "bitrate" : 0,
    "duration" : 0,
    "title" : null,
    "properties" : null,
    "alternate" : [ {
      "href" : "https://img.abctruyen.xyz/uploads/19429/chuong-14/8.jpg",
      "type" : "image/jpeg",
      "bitrate" : 0,
      "duration" : 0,
      "title" : null,
      "properties" : null,
      "alternate" : null
    }, {
      "href" : "https://i2.wp.com/img.abctruyen.xyz/uploads/19429/chuong-14/8.jpg",
      "type" : "image/jpeg",
      "bitrate" : 0,
      "duration" : 0,
      "title" : null,
      "properties" : null,
      "alternate" : null
    } ]
  }, {
    "href" : "https://raw.githubusercontent.com/tracuumasothue40/comic_storage_two7/main/IMAGE/IMAGE_02f81e1c6377ca00b2ecc19daea2d4ba_387e9bb2d5522e2a1eb69646c6949884_70b613e8019572573036aacd41a42f73.jpg",
    "type" : "image/jpeg",
    "bitrate" : 0,
    "duration" : 0,
    "title" : null,
    "properties" : null,
    "alternate" : [ {
      "href" : "https://img.abctruyen.xyz/uploads/19429/chuong-14/9.jpg",
      "type" : "image/jpeg",
      "bitrate" : 0,
      "duration" : 0,
      "title" : null,
      "properties" : null,
      "alternate" : null
    }, {
      "href" : "https://i2.wp.com/img.abctruyen.xyz/uploads/19429/chuong-14/9.jpg",
      "type" : "image/jpeg",
      "bitrate" : 0,
      "duration" : 0,
      "title" : null,
      "properties" : null,
      "alternate" : null
    } ]
  }, {
    "href" : "https://raw.githubusercontent.com/tracuumasothue40/comic_storage_two7/main/IMAGE/IMAGE_02f81e1c6377ca00b2ecc19daea2d4ba_387e9bb2d5522e2a1eb69646c6949884_abffc3863621f2dffc3c453f82399c83.jpg",
    "type" : "image/jpeg",
    "bitrate" : 0,
    "duration" : 0,
    "title" : null,
    "properties" : null,
    "alternate" : [ {
      "href" : "https://img.abctruyen.xyz/uploads/19429/chuong-14/10.jpg",
      "type" : "image/jpeg",
      "bitrate" : 0,
      "duration" : 0,
      "title" : null,
      "properties" : null,
      "alternate" : null
    }, {
      "href" : "https://i2.wp.com/img.abctruyen.xyz/uploads/19429/chuong-14/10.jpg",
      "type" : "image/jpeg",
      "bitrate" : 0,
      "duration" : 0,
      "title" : null,
      "properties" : null,
      "alternate" : null
    } ]
  }, {
    "href" : "https://raw.githubusercontent.com/tracuumasothue40/comic_storage_two7/main/IMAGE/IMAGE_02f81e1c6377ca00b2ecc19daea2d4ba_387e9bb2d5522e2a1eb69646c6949884_6cdf53a7fb5ca0313dfb100c5f074f45.jpg",
    "type" : "image/jpeg",
    "bitrate" : 0,
    "duration" : 0,
    "title" : null,
    "properties" : null,
    "alternate" : [ {
      "href" : "https://img.abctruyen.xyz/uploads/19429/chuong-14/11.jpg",
      "type" : "image/jpeg",
      "bitrate" : 0,
      "duration" : 0,
      "title" : null,
      "properties" : null,
      "alternate" : null
    }, {
      "href" : "https://i2.wp.com/img.abctruyen.xyz/uploads/19429/chuong-14/11.jpg",
      "type" : "image/jpeg",
      "bitrate" : 0,
      "duration" : 0,
      "title" : null,
      "properties" : null,
      "alternate" : null
    } ]
  }, {
    "href" : "https://raw.githubusercontent.com/tracuumasothue40/comic_storage_two7/main/IMAGE/IMAGE_02f81e1c6377ca00b2ecc19daea2d4ba_387e9bb2d5522e2a1eb69646c6949884_4eb02d0e4759b92969099668a943a518.jpg",
    "type" : "image/jpeg",
    "bitrate" : 0,
    "duration" : 0,
    "title" : null,
    "properties" : null,
    "alternate" : [ {
      "href" : "https://img.abctruyen.xyz/uploads/19429/chuong-14/12.jpg",
      "type" : "image/jpeg",
      "bitrate" : 0,
      "duration" : 0,
      "title" : null,
      "properties" : null,
      "alternate" : null
    }, {
      "href" : "https://i2.wp.com/img.abctruyen.xyz/uploads/19429/chuong-14/12.jpg",
      "type" : "image/jpeg",
      "bitrate" : 0,
      "duration" : 0,
      "title" : null,
      "properties" : null,
      "alternate" : null
    } ]
  }, {
    "href" : "https://raw.githubusercontent.com/tracuumasothue40/comic_storage_two7/main/IMAGE/IMAGE_02f81e1c6377ca00b2ecc19daea2d4ba_387e9bb2d5522e2a1eb69646c6949884_c5ae6bcb3ac1db8cd8c2b014466a6888.jpg",
    "type" : "image/jpeg",
    "bitrate" : 0,
    "duration" : 0,
    "title" : null,
    "properties" : null,
    "alternate" : [ {
      "href" : "https://img.abctruyen.xyz/uploads/19429/chuong-14/13.jpg",
      "type" : "image/jpeg",
      "bitrate" : 0,
      "duration" : 0,
      "title" : null,
      "properties" : null,
      "alternate" : null
    }, {
      "href" : "https://i2.wp.com/img.abctruyen.xyz/uploads/19429/chuong-14/13.jpg",
      "type" : "image/jpeg",
      "bitrate" : 0,
      "duration" : 0,
      "title" : null,
      "properties" : null,
      "alternate" : null
    } ]
  }, {
    "href" : "https://raw.githubusercontent.com/tracuumasothue40/comic_storage_two7/main/IMAGE/IMAGE_02f81e1c6377ca00b2ecc19daea2d4ba_387e9bb2d5522e2a1eb69646c6949884_e2fee9bdab5fb23e4fb0b35ea742043b.jpg",
    "type" : "image/jpeg",
    "bitrate" : 0,
    "duration" : 0,
    "title" : null,
    "properties" : null,
    "alternate" : [ {
      "href" : "https://img.abctruyen.xyz/uploads/19429/chuong-14/14.jpg",
      "type" : "image/jpeg",
      "bitrate" : 0,
      "duration" : 0,
      "title" : null,
      "properties" : null,
      "alternate" : null
    }, {
      "href" : "https://i2.wp.com/img.abctruyen.xyz/uploads/19429/chuong-14/14.jpg",
      "type" : "image/jpeg",
      "bitrate" : 0,
      "duration" : 0,
      "title" : null,
      "properties" : null,
      "alternate" : null
    } ]
  }, {
    "href" : "https://raw.githubusercontent.com/tracuumasothue40/comic_storage_two7/main/IMAGE/IMAGE_02f81e1c6377ca00b2ecc19daea2d4ba_387e9bb2d5522e2a1eb69646c6949884_56ac56850fb3138929bef42c94fdb9c0.jpg",
    "type" : "image/jpeg",
    "bitrate" : 0,
    "duration" : 0,
    "title" : null,
    "properties" : null,
    "alternate" : [ {
      "href" : "https://img.abctruyen.xyz/uploads/19429/chuong-14/15.jpg",
      "type" : "image/jpeg",
      "bitrate" : 0,
      "duration" : 0,
      "title" : null,
      "properties" : null,
      "alternate" : null
    }, {
      "href" : "https://i2.wp.com/img.abctruyen.xyz/uploads/19429/chuong-14/15.jpg",
      "type" : "image/jpeg",
      "bitrate" : 0,
      "duration" : 0,
      "title" : null,
      "properties" : null,
      "alternate" : null
    } ]
  }, {
    "href" : "https://raw.githubusercontent.com/tracuumasothue40/comic_storage_two7/main/IMAGE/IMAGE_02f81e1c6377ca00b2ecc19daea2d4ba_387e9bb2d5522e2a1eb69646c6949884_5d0cf46606ad0eeff0d3e5dc4469c30e.jpg",
    "type" : "image/jpeg",
    "bitrate" : 0,
    "duration" : 0,
    "title" : null,
    "properties" : null,
    "alternate" : [ {
      "href" : "https://img.abctruyen.xyz/uploads/19429/chuong-14/16.jpg",
      "type" : "image/jpeg",
      "bitrate" : 0,
      "duration" : 0,
      "title" : null,
      "properties" : null,
      "alternate" : null
    }, {
      "href" : "https://i2.wp.com/img.abctruyen.xyz/uploads/19429/chuong-14/16.jpg",
      "type" : "image/jpeg",
      "bitrate" : 0,
      "duration" : 0,
      "title" : null,
      "properties" : null,
      "alternate" : null
    } ]
  }, {
    "href" : "https://raw.githubusercontent.com/tracuumasothue40/comic_storage_two7/main/IMAGE/IMAGE_02f81e1c6377ca00b2ecc19daea2d4ba_387e9bb2d5522e2a1eb69646c6949884_2024ed080b3a291039fd747a6193ac6f.jpg",
    "type" : "image/jpeg",
    "bitrate" : 0,
    "duration" : 0,
    "title" : null,
    "properties" : null,
    "alternate" : [ {
      "href" : "https://img.abctruyen.xyz/uploads/19429/chuong-14/17.jpg",
      "type" : "image/jpeg",
      "bitrate" : 0,
      "duration" : 0,
      "title" : null,
      "properties" : null,
      "alternate" : null
    }, {
      "href" : "https://i2.wp.com/img.abctruyen.xyz/uploads/19429/chuong-14/17.jpg",
      "type" : "image/jpeg",
      "bitrate" : 0,
      "duration" : 0,
      "title" : null,
      "properties" : null,
      "alternate" : null
    } ]
  }, {
    "href" : "https://raw.githubusercontent.com/tracuumasothue40/comic_storage_two7/main/IMAGE/IMAGE_02f81e1c6377ca00b2ecc19daea2d4ba_387e9bb2d5522e2a1eb69646c6949884_cdc33f9c3c751e3ecacbe0cb75eb1a0a.jpg",
    "type" : "image/jpeg",
    "bitrate" : 0,
    "duration" : 0,
    "title" : null,
    "properties" : null,
    "alternate" : [ {
      "href" : "https://img.abctruyen.xyz/uploads/19429/chuong-14/18.jpg",
      "type" : "image/jpeg",
      "bitrate" : 0,
      "duration" : 0,
      "title" : null,
      "properties" : null,
      "alternate" : null
    }, {
      "href" : "https://i2.wp.com/img.abctruyen.xyz/uploads/19429/chuong-14/18.jpg",
      "type" : "image/jpeg",
      "bitrate" : 0,
      "duration" : 0,
      "title" : null,
      "properties" : null,
      "alternate" : null
    } ]
  }, {
    "href" : "https://raw.githubusercontent.com/tracuumasothue40/comic_storage_two7/main/IMAGE/IMAGE_02f81e1c6377ca00b2ecc19daea2d4ba_387e9bb2d5522e2a1eb69646c6949884_6a1ba57e92c4d877582991d44dc28177.jpg",
    "type" : "image/jpeg",
    "bitrate" : 0,
    "duration" : 0,
    "title" : null,
    "properties" : null,
    "alternate" : [ {
      "href" : "https://img.abctruyen.xyz/uploads/19429/chuong-14/19.jpg",
      "type" : "image/jpeg",
      "bitrate" : 0,
      "duration" : 0,
      "title" : null,
      "properties" : null,
      "alternate" : null
    }, {
      "href" : "https://i2.wp.com/img.abctruyen.xyz/uploads/19429/chuong-14/19.jpg",
      "type" : "image/jpeg",
      "bitrate" : 0,
      "duration" : 0,
      "title" : null,
      "properties" : null,
      "alternate" : null
    } ]
  }, {
    "href" : "https://raw.githubusercontent.com/tracuumasothue40/comic_storage_two7/main/IMAGE/IMAGE_02f81e1c6377ca00b2ecc19daea2d4ba_387e9bb2d5522e2a1eb69646c6949884_f8a006b8798ac1115dc0a1cf4252f2da.jpg",
    "type" : "image/jpeg",
    "bitrate" : 0,
    "duration" : 0,
    "title" : null,
    "properties" : null,
    "alternate" : [ {
      "href" : "https://img.abctruyen.xyz/uploads/19429/chuong-14/20.jpg",
      "type" : "image/jpeg",
      "bitrate" : 0,
      "duration" : 0,
      "title" : null,
      "properties" : null,
      "alternate" : null
    }, {
      "href" : "https://i2.wp.com/img.abctruyen.xyz/uploads/19429/chuong-14/20.jpg",
      "type" : "image/jpeg",
      "bitrate" : 0,
      "duration" : 0,
      "title" : null,
      "properties" : null,
      "alternate" : null
    } ]
  }, {
    "href" : "https://raw.githubusercontent.com/tracuumasothue40/comic_storage_two7/main/IMAGE/IMAGE_02f81e1c6377ca00b2ecc19daea2d4ba_387e9bb2d5522e2a1eb69646c6949884_98d34308591b59e2f22f8f388c73296d.jpg",
    "type" : "image/jpeg",
    "bitrate" : 0,
    "duration" : 0,
    "title" : null,
    "properties" : null,
    "alternate" : [ {
      "href" : "https://img.abctruyen.xyz/uploads/19429/chuong-14/21.jpg",
      "type" : "image/jpeg",
      "bitrate" : 0,
      "duration" : 0,
      "title" : null,
      "properties" : null,
      "alternate" : null
    }, {
      "href" : "https://i2.wp.com/img.abctruyen.xyz/uploads/19429/chuong-14/21.jpg",
      "type" : "image/jpeg",
      "bitrate" : 0,
      "duration" : 0,
      "title" : null,
      "properties" : null,
      "alternate" : null
    } ]
  }, {
    "href" : "https://raw.githubusercontent.com/tracuumasothue40/comic_storage_two7/main/IMAGE/IMAGE_02f81e1c6377ca00b2ecc19daea2d4ba_387e9bb2d5522e2a1eb69646c6949884_ed40b300953ca2a7d46e008393f21736.jpg",
    "type" : "image/jpeg",
    "bitrate" : 0,
    "duration" : 0,
    "title" : null,
    "properties" : null,
    "alternate" : [ {
      "href" : "https://img.abctruyen.xyz/uploads/19429/chuong-14/22.jpg",
      "type" : "image/jpeg",
      "bitrate" : 0,
      "duration" : 0,
      "title" : null,
      "properties" : null,
      "alternate" : null
    }, {
      "href" : "https://i2.wp.com/img.abctruyen.xyz/uploads/19429/chuong-14/22.jpg",
      "type" : "image/jpeg",
      "bitrate" : 0,
      "duration" : 0,
      "title" : null,
      "properties" : null,
      "alternate" : null
    } ]
  }, {
    "href" : "https://raw.githubusercontent.com/tracuumasothue40/comic_storage_two7/main/IMAGE/IMAGE_02f81e1c6377ca00b2ecc19daea2d4ba_387e9bb2d5522e2a1eb69646c6949884_a6e6933c576a42883798f5dab455c484.jpg",
    "type" : "image/jpeg",
    "bitrate" : 0,
    "duration" : 0,
    "title" : null,
    "properties" : null,
    "alternate" : [ {
      "href" : "https://img.abctruyen.xyz/uploads/19429/chuong-14/23.jpg",
      "type" : "image/jpeg",
      "bitrate" : 0,
      "duration" : 0,
      "title" : null,
      "properties" : null,
      "alternate" : null
    }, {
      "href" : "https://i2.wp.com/img.abctruyen.xyz/uploads/19429/chuong-14/23.jpg",
      "type" : "image/jpeg",
      "bitrate" : 0,
      "duration" : 0,
      "title" : null,
      "properties" : null,
      "alternate" : null
    } ]
  }, {
    "href" : "https://raw.githubusercontent.com/tracuumasothue40/comic_storage_two7/main/IMAGE/IMAGE_02f81e1c6377ca00b2ecc19daea2d4ba_387e9bb2d5522e2a1eb69646c6949884_dc17548941a2c44e5d631261b575cf77.jpg",
    "type" : "image/jpeg",
    "bitrate" : 0,
    "duration" : 0,
    "title" : null,
    "properties" : null,
    "alternate" : [ {
      "href" : "https://img.abctruyen.xyz/uploads/19429/chuong-14/24.jpg",
      "type" : "image/jpeg",
      "bitrate" : 0,
      "duration" : 0,
      "title" : null,
      "properties" : null,
      "alternate" : null
    }, {
      "href" : "https://i2.wp.com/img.abctruyen.xyz/uploads/19429/chuong-14/24.jpg",
      "type" : "image/jpeg",
      "bitrate" : 0,
      "duration" : 0,
      "title" : null,
      "properties" : null,
      "alternate" : null
    } ]
  }, {
    "href" : "https://raw.githubusercontent.com/tracuumasothue40/comic_storage_two7/main/IMAGE/IMAGE_02f81e1c6377ca00b2ecc19daea2d4ba_387e9bb2d5522e2a1eb69646c6949884_aff12ac71894b6d4701b58a37be27988.jpg",
    "type" : "image/jpeg",
    "bitrate" : 0,
    "duration" : 0,
    "title" : null,
    "properties" : null,
    "alternate" : [ {
      "href" : "https://img.abctruyen.xyz/uploads/19429/chuong-14/25.jpg",
      "type" : "image/jpeg",
      "bitrate" : 0,
      "duration" : 0,
      "title" : null,
      "properties" : null,
      "alternate" : null
    }, {
      "href" : "https://i2.wp.com/img.abctruyen.xyz/uploads/19429/chuong-14/25.jpg",
      "type" : "image/jpeg",
      "bitrate" : 0,
      "duration" : 0,
      "title" : null,
      "properties" : null,
      "alternate" : null
    } ]
  }, {
    "href" : "https://raw.githubusercontent.com/tracuumasothue40/comic_storage_two7/main/IMAGE/IMAGE_02f81e1c6377ca00b2ecc19daea2d4ba_387e9bb2d5522e2a1eb69646c6949884_7167fe99d472bb1a74c50448033939ab.jpg",
    "type" : "image/jpeg",
    "bitrate" : 0,
    "duration" : 0,
    "title" : null,
    "properties" : null,
    "alternate" : [ {
      "href" : "https://img.abctruyen.xyz/uploads/19429/chuong-14/26.jpg",
      "type" : "image/jpeg",
      "bitrate" : 0,
      "duration" : 0,
      "title" : null,
      "properties" : null,
      "alternate" : null
    }, {
      "href" : "https://i2.wp.com/img.abctruyen.xyz/uploads/19429/chuong-14/26.jpg",
      "type" : "image/jpeg",
      "bitrate" : 0,
      "duration" : 0,
      "title" : null,
      "properties" : null,
      "alternate" : null
    } ]
  }, {
    "href" : "https://raw.githubusercontent.com/tracuumasothue40/comic_storage_two7/main/IMAGE/IMAGE_02f81e1c6377ca00b2ecc19daea2d4ba_387e9bb2d5522e2a1eb69646c6949884_a5c7f47ddad5687e90acd8eeda8d2527.jpg",
    "type" : "image/jpeg",
    "bitrate" : 0,
    "duration" : 0,
    "title" : null,
    "properties" : null,
    "alternate" : [ {
      "href" : "https://img.abctruyen.xyz/uploads/19429/chuong-14/27.jpg",
      "type" : "image/jpeg",
      "bitrate" : 0,
      "duration" : 0,
      "title" : null,
      "properties" : null,
      "alternate" : null
    }, {
      "href" : "https://i2.wp.com/img.abctruyen.xyz/uploads/19429/chuong-14/27.jpg",
      "type" : "image/jpeg",
      "bitrate" : 0,
      "duration" : 0,
      "title" : null,
      "properties" : null,
      "alternate" : null
    } ]
  }, {
    "href" : "https://raw.githubusercontent.com/tracuumasothue40/comic_storage_two7/main/IMAGE/IMAGE_02f81e1c6377ca00b2ecc19daea2d4ba_387e9bb2d5522e2a1eb69646c6949884_a0006ac9e61bf6edd4848b1805e6f317.jpg",
    "type" : "image/jpeg",
    "bitrate" : 0,
    "duration" : 0,
    "title" : null,
    "properties" : null,
    "alternate" : [ {
      "href" : "https://img.abctruyen.xyz/uploads/19429/chuong-14/28.jpg",
      "type" : "image/jpeg",
      "bitrate" : 0,
      "duration" : 0,
      "title" : null,
      "properties" : null,
      "alternate" : null
    }, {
      "href" : "https://i2.wp.com/img.abctruyen.xyz/uploads/19429/chuong-14/28.jpg",
      "type" : "image/jpeg",
      "bitrate" : 0,
      "duration" : 0,
      "title" : null,
      "properties" : null,
      "alternate" : null
    } ]
  }, {
    "href" : "https://raw.githubusercontent.com/tracuumasothue40/comic_storage_two7/main/IMAGE/IMAGE_02f81e1c6377ca00b2ecc19daea2d4ba_387e9bb2d5522e2a1eb69646c6949884_0382c7e506b5a828e8da0beee9b84305.jpg",
    "type" : "image/jpeg",
    "bitrate" : 0,
    "duration" : 0,
    "title" : null,
    "properties" : null,
    "alternate" : [ {
      "href" : "https://img.abctruyen.xyz/uploads/19429/chuong-14/29.jpg",
      "type" : "image/jpeg",
      "bitrate" : 0,
      "duration" : 0,
      "title" : null,
      "properties" : null,
      "alternate" : null
    }, {
      "href" : "https://i2.wp.com/img.abctruyen.xyz/uploads/19429/chuong-14/29.jpg",
      "type" : "image/jpeg",
      "bitrate" : 0,
      "duration" : 0,
      "title" : null,
      "properties" : null,
      "alternate" : null
    } ]
  }, {
    "href" : "https://raw.githubusercontent.com/tracuumasothue40/comic_storage_two7/main/IMAGE/IMAGE_02f81e1c6377ca00b2ecc19daea2d4ba_387e9bb2d5522e2a1eb69646c6949884_ddb3e09b78195250ca9811bc2305442d.jpg",
    "type" : "image/jpeg",
    "bitrate" : 0,
    "duration" : 0,
    "title" : null,
    "properties" : null,
    "alternate" : [ {
      "href" : "https://img.abctruyen.xyz/uploads/19429/chuong-14/30.jpg",
      "type" : "image/jpeg",
      "bitrate" : 0,
      "duration" : 0,
      "title" : null,
      "properties" : null,
      "alternate" : null
    }, {
      "href" : "https://i2.wp.com/img.abctruyen.xyz/uploads/19429/chuong-14/30.jpg",
      "type" : "image/jpeg",
      "bitrate" : 0,
      "duration" : 0,
      "title" : null,
      "properties" : null,
      "alternate" : null
    } ]
  }, {
    "href" : "https://raw.githubusercontent.com/tracuumasothue40/comic_storage_two7/main/IMAGE/IMAGE_02f81e1c6377ca00b2ecc19daea2d4ba_387e9bb2d5522e2a1eb69646c6949884_554c387046693194872b70741508c7a1.jpg",
    "type" : "image/jpeg",
    "bitrate" : 0,
    "duration" : 0,
    "title" : null,
    "properties" : null,
    "alternate" : [ {
      "href" : "https://img.abctruyen.xyz/uploads/19429/chuong-14/31.jpg",
      "type" : "image/jpeg",
      "bitrate" : 0,
      "duration" : 0,
      "title" : null,
      "properties" : null,
      "alternate" : null
    }, {
      "href" : "https://i2.wp.com/img.abctruyen.xyz/uploads/19429/chuong-14/31.jpg",
      "type" : "image/jpeg",
      "bitrate" : 0,
      "duration" : 0,
      "title" : null,
      "properties" : null,
      "alternate" : null
    } ]
  }, {
    "href" : "https://raw.githubusercontent.com/tracuumasothue40/comic_storage_two7/main/IMAGE/IMAGE_02f81e1c6377ca00b2ecc19daea2d4ba_387e9bb2d5522e2a1eb69646c6949884_4db7c772938f003260699b6d329bce74.jpg",
    "type" : "image/jpeg",
    "bitrate" : 0,
    "duration" : 0,
    "title" : null,
    "properties" : null,
    "alternate" : [ {
      "href" : "https://img.abctruyen.xyz/uploads/19429/chuong-14/32.jpg",
      "type" : "image/jpeg",
      "bitrate" : 0,
      "duration" : 0,
      "title" : null,
      "properties" : null,
      "alternate" : null
    }, {
      "href" : "https://i2.wp.com/img.abctruyen.xyz/uploads/19429/chuong-14/32.jpg",
      "type" : "image/jpeg",
      "bitrate" : 0,
      "duration" : 0,
      "title" : null,
      "properties" : null,
      "alternate" : null
    } ]
  }, {
    "href" : "https://raw.githubusercontent.com/tracuumasothue40/comic_storage_two7/main/IMAGE/IMAGE_02f81e1c6377ca00b2ecc19daea2d4ba_387e9bb2d5522e2a1eb69646c6949884_d61ffd360ac8559dd6f04e1ec1e49143.jpg",
    "type" : "image/jpeg",
    "bitrate" : 0,
    "duration" : 0,
    "title" : null,
    "properties" : null,
    "alternate" : [ {
      "href" : "https://img.abctruyen.xyz/uploads/19429/chuong-14/33.jpg",
      "type" : "image/jpeg",
      "bitrate" : 0,
      "duration" : 0,
      "title" : null,
      "properties" : null,
      "alternate" : null
    }, {
      "href" : "https://i2.wp.com/img.abctruyen.xyz/uploads/19429/chuong-14/33.jpg",
      "type" : "image/jpeg",
      "bitrate" : 0,
      "duration" : 0,
      "title" : null,
      "properties" : null,
      "alternate" : null
    } ]
  }, {
    "href" : "https://raw.githubusercontent.com/tracuumasothue40/comic_storage_two7/main/IMAGE/IMAGE_02f81e1c6377ca00b2ecc19daea2d4ba_387e9bb2d5522e2a1eb69646c6949884_d486d5d5ad7443b2318e9c17fddf86a9.jpg",
    "type" : "image/jpeg",
    "bitrate" : 0,
    "duration" : 0,
    "title" : null,
    "properties" : null,
    "alternate" : [ {
      "href" : "https://img.abctruyen.xyz/uploads/19429/chuong-14/34.jpg",
      "type" : "image/jpeg",
      "bitrate" : 0,
      "duration" : 0,
      "title" : null,
      "properties" : null,
      "alternate" : null
    }, {
      "href" : "https://i2.wp.com/img.abctruyen.xyz/uploads/19429/chuong-14/34.jpg",
      "type" : "image/jpeg",
      "bitrate" : 0,
      "duration" : 0,
      "title" : null,
      "properties" : null,
      "alternate" : null
    } ]
  }, {
    "href" : "https://raw.githubusercontent.com/tracuumasothue40/comic_storage_two7/main/IMAGE/IMAGE_02f81e1c6377ca00b2ecc19daea2d4ba_387e9bb2d5522e2a1eb69646c6949884_e2776e7c9bdeafcd6110cec7988c009f.jpg",
    "type" : "image/jpeg",
    "bitrate" : 0,
    "duration" : 0,
    "title" : null,
    "properties" : null,
    "alternate" : [ {
      "href" : "https://img.abctruyen.xyz/uploads/19429/chuong-14/35.jpg",
      "type" : "image/jpeg",
      "bitrate" : 0,
      "duration" : 0,
      "title" : null,
      "properties" : null,
      "alternate" : null
    }, {
      "href" : "https://i2.wp.com/img.abctruyen.xyz/uploads/19429/chuong-14/35.jpg",
      "type" : "image/jpeg",
      "bitrate" : 0,
      "duration" : 0,
      "title" : null,
      "properties" : null,
      "alternate" : null
    } ]
  }, {
    "href" : "https://raw.githubusercontent.com/tracuumasothue40/comic_storage_two7/main/IMAGE/IMAGE_02f81e1c6377ca00b2ecc19daea2d4ba_387e9bb2d5522e2a1eb69646c6949884_d7404c58dade8909d892bcd2622327f5.jpg",
    "type" : "image/jpeg",
    "bitrate" : 0,
    "duration" : 0,
    "title" : null,
    "properties" : null,
    "alternate" : [ {
      "href" : "https://img.abctruyen.xyz/uploads/19429/chuong-14/36.jpg",
      "type" : "image/jpeg",
      "bitrate" : 0,
      "duration" : 0,
      "title" : null,
      "properties" : null,
      "alternate" : null
    }, {
      "href" : "https://i2.wp.com/img.abctruyen.xyz/uploads/19429/chuong-14/36.jpg",
      "type" : "image/jpeg",
      "bitrate" : 0,
      "duration" : 0,
      "title" : null,
      "properties" : null,
      "alternate" : null
    } ]
  }, {
    "href" : "https://raw.githubusercontent.com/tracuumasothue40/comic_storage_two7/main/IMAGE/IMAGE_02f81e1c6377ca00b2ecc19daea2d4ba_387e9bb2d5522e2a1eb69646c6949884_46bb7812f8146ab44c32771c15688a1d.jpg",
    "type" : "image/jpeg",
    "bitrate" : 0,
    "duration" : 0,
    "title" : null,
    "properties" : null,
    "alternate" : [ {
      "href" : "https://img.abctruyen.xyz/uploads/19429/chuong-14/37.jpg",
      "type" : "image/jpeg",
      "bitrate" : 0,
      "duration" : 0,
      "title" : null,
      "properties" : null,
      "alternate" : null
    }, {
      "href" : "https://i2.wp.com/img.abctruyen.xyz/uploads/19429/chuong-14/37.jpg",
      "type" : "image/jpeg",
      "bitrate" : 0,
      "duration" : 0,
      "title" : null,
      "properties" : null,
      "alternate" : null
    } ]
  }, {
    "href" : "https://raw.githubusercontent.com/tracuumasothue40/comic_storage_two7/main/IMAGE/IMAGE_02f81e1c6377ca00b2ecc19daea2d4ba_387e9bb2d5522e2a1eb69646c6949884_74c1f343717d5b59ae748e016014a2d9.jpg",
    "type" : "image/jpeg",
    "bitrate" : 0,
    "duration" : 0,
    "title" : null,
    "properties" : null,
    "alternate" : [ {
      "href" : "https://img.abctruyen.xyz/uploads/19429/chuong-14/38.jpg",
      "type" : "image/jpeg",
      "bitrate" : 0,
      "duration" : 0,
      "title" : null,
      "properties" : null,
      "alternate" : null
    }, {
      "href" : "https://i2.wp.com/img.abctruyen.xyz/uploads/19429/chuong-14/38.jpg",
      "type" : "image/jpeg",
      "bitrate" : 0,
      "duration" : 0,
      "title" : null,
      "properties" : null,
      "alternate" : null
    } ]
  }, {
    "href" : "https://raw.githubusercontent.com/tracuumasothue40/comic_storage_two7/main/IMAGE/IMAGE_02f81e1c6377ca00b2ecc19daea2d4ba_387e9bb2d5522e2a1eb69646c6949884_ab92164ee81be6c4b432f0e604f92059.jpg",
    "type" : "image/jpeg",
    "bitrate" : 0,
    "duration" : 0,
    "title" : null,
    "properties" : null,
    "alternate" : [ {
      "href" : "https://img.abctruyen.xyz/uploads/19429/chuong-14/39.jpg",
      "type" : "image/jpeg",
      "bitrate" : 0,
      "duration" : 0,
      "title" : null,
      "properties" : null,
      "alternate" : null
    }, {
      "href" : "https://i2.wp.com/img.abctruyen.xyz/uploads/19429/chuong-14/39.jpg",
      "type" : "image/jpeg",
      "bitrate" : 0,
      "duration" : 0,
      "title" : null,
      "properties" : null,
      "alternate" : null
    } ]
  }, {
    "href" : "https://raw.githubusercontent.com/tracuumasothue40/comic_storage_two7/main/IMAGE/IMAGE_02f81e1c6377ca00b2ecc19daea2d4ba_387e9bb2d5522e2a1eb69646c6949884_66cf004fc4e3dde077f3b854f4336257.jpg",
    "type" : "image/jpeg",
    "bitrate" : 0,
    "duration" : 0,
    "title" : null,
    "properties" : null,
    "alternate" : [ {
      "href" : "https://img.abctruyen.xyz/uploads/19429/chuong-14/40.jpg",
      "type" : "image/jpeg",
      "bitrate" : 0,
      "duration" : 0,
      "title" : null,
      "properties" : null,
      "alternate" : null
    }, {
      "href" : "https://i2.wp.com/img.abctruyen.xyz/uploads/19429/chuong-14/40.jpg",
      "type" : "image/jpeg",
      "bitrate" : 0,
      "duration" : 0,
      "title" : null,
      "properties" : null,
      "alternate" : null
    } ]
  } ],
  "toc" : null,
  "@context" : "https://readium.org/webpub-manifest/context.jsonld"
}